futureproof/__init__.py
futureproof/executors.py
futureproof/task_manager.py
futureproof-0.3.1.dist-info/LICENSE.md
futureproof-0.3.1.dist-info/METADATA
futureproof-0.3.1.dist-info/WHEEL
futureproof-0.3.1.dist-info/top_level.txt
futureproof-0.3.1.dist-info/RECORD
