Metadata-Version: 2.1
Name: futureproof
Version: 0.3.1
Summary: Bulletproof concurrent.futures
Home-page: https://github.com/yeraydiazdiaz/futureproof
Author: Yeray Diaz Diaz
Author-email: yeraydiazdiaz@gmail.com
License: MIT
Keywords: concurrent futures multithreading
Platform: UNKNOWN
Classifier: Development Status :: 3 - Alpha
Classifier: Intended Audience :: Developers
Classifier: License :: OSI Approved :: MIT License
Classifier: Operating System :: OS Independent
Classifier: Programming Language :: Python
Classifier: Programming Language :: Python :: 3
Classifier: Programming Language :: Python :: 3.6
Classifier: Programming Language :: Python :: 3.7
Classifier: Programming Language :: Python :: 3.8
Classifier: Programming Language :: Python :: 3.9
Classifier: Programming Language :: Python :: 3.10
Classifier: Programming Language :: Python :: Implementation :: CPython
Classifier: Topic :: Software Development :: Libraries :: Python Modules
Provides-Extra: tests
Provides-Extra: docs
Provides-Extra: dev
License-File: LICENSE.md
